tucker_riemopt/__init__.py
tucker_riemopt/backend/__init__.py
tucker_riemopt/backend/backend.py
tucker_riemopt/backend/jax_backend.py
tucker_riemopt/backend/pytorch_backend.py
tucker_riemopt/sf_tucker/matrix.py
tucker_riemopt/sf_tucker/riemannian.py
tucker_riemopt/sf_tucker/sf_tucker.py
tucker_riemopt/sparse.py
tucker_riemopt/tucker/matrix.py
tucker_riemopt/tucker/riemannian.py
tucker_riemopt/tucker/tucker.py
tucker_riemopt-1.0.1.dist-info/LICENSE
tucker_riemopt-1.0.1.dist-info/METADATA
tucker_riemopt-1.0.1.dist-info/WHEEL
tucker_riemopt-1.0.1.dist-info/RECORD
