Metadata-Version: 2.1
Name: tucker-riemopt
Version: 1.0.1
Summary: Tucker toolbox for Riemannian optimization.
License: MIT
Author: johanddc
Author-email: ivan.peshekhonov@gmail.com
Requires-Python: >=3.9,<4.0
Classifier: License :: OSI Approved :: MIT License
Classifier: Programming Language :: Python :: 3
Classifier: Programming Language :: Python :: 3.9
Classifier: Programming Language :: Python :: 3.10
Classifier: Programming Language :: Python :: 3.11
Classifier: Programming Language :: Python :: 3.12
Provides-Extra: jax
Provides-Extra: torch
Requires-Dist: jax (>=0.4.23,<0.5.0) ; extra == "jax"
Requires-Dist: numpy (>=1.21.4,<2.0.0)
Requires-Dist: opt-einsum (>=3.3.0,<4.0.0)
Requires-Dist: scipy (>=1.8.0,<2.0.0)
Requires-Dist: torch (>=2.0.0,<3.0.0) ; extra == "torch"
